sescam/__init__.py
sescam/model.py
sescam/sescam_api.py
sescam-0.2.1.dist-info/METADATA
sescam-0.2.1.dist-info/WHEEL
sescam-0.2.1.dist-info/entry_points.txt
sescam-0.2.1.dist-info/licenses/LICENSE
sescam-0.2.1.dist-info/RECORD
