Metadata-Version: 2.4
Name: sescam
Version: 0.2.1
Summary: Add your description here
Author-email: José Luis Segura Lucas <josel.segura@gmx.es>
License-File: LICENSE
Requires-Python: >=3.13
Requires-Dist: requests>=2.32.3
Provides-Extra: linting
Requires-Dist: ruff>=0.11.6; extra == 'linting'
